odoo/addons/telecom/__init__.py
odoo/addons/telecom/__manifest__.py
odoo/addons/telecom/data/contract_template.xml
odoo/addons/telecom/data/ir_cron.xml
odoo/addons/telecom/data/ir_module_category.xml
odoo/addons/telecom/data/previous.provider.csv
odoo/addons/telecom/data/product_attribute.xml
odoo/addons/telecom/data/product_categories.xml
odoo/addons/telecom/data/product_category.xml
odoo/addons/telecom/data/product_template.xml
odoo/addons/telecom/data/res_company.xml
odoo/addons/telecom/data/service_supplier.xml
odoo/addons/telecom/data/service_technology.xml
odoo/addons/telecom/demo/base_substate.xml
odoo/addons/telecom/demo/base_substate_type.xml
odoo/addons/telecom/demo/target_state_value.xml
odoo/addons/telecom/listeners/__init__.py
odoo/addons/telecom/listeners/crm_lead_listener.py
odoo/addons/telecom/migrations/12.0.0.0.9/post-calculate-isp-info-reference.py
odoo/addons/telecom/migrations/12.0.0.0.9/pre-calculate-isp-info-reference.py
odoo/addons/telecom/models/__init__.py
odoo/addons/telecom/models/contract.py
odoo/addons/telecom/models/crm_lead.py
odoo/addons/telecom/models/crm_lead_line.py
odoo/addons/telecom/models/previous_provider.py
odoo/addons/telecom/models/product_product.py
odoo/addons/telecom/models/product_template.py
odoo/addons/telecom/models/res_company.py
odoo/addons/telecom/models/res_config_settings.py
odoo/addons/telecom/models/sale_order.py
odoo/addons/telecom/models/service_supplier.py
odoo/addons/telecom/models/service_technology.py
odoo/addons/telecom/models/sub_state.py
odoo/addons/telecom/models/telecom_mixin.py
odoo/addons/telecom/models/isp_info/__init__.py
odoo/addons/telecom/models/isp_info/base.py
odoo/addons/telecom/models/isp_info/broadband.py
odoo/addons/telecom/models/isp_info/isp_info_mixin.py
odoo/addons/telecom/models/isp_info/landline.py
odoo/addons/telecom/models/isp_info/mobile.py
odoo/addons/telecom/security/ir.model.access.csv
odoo/addons/telecom/security/res_groups.xml
odoo/addons/telecom/services/__init__.py
odoo12_addon_telecom-12.0.0.1.0.dist-info/METADATA
odoo12_addon_telecom-12.0.0.1.0.dist-info/WHEEL
odoo12_addon_telecom-12.0.0.1.0.dist-info/top_level.txt
odoo12_addon_telecom-12.0.0.1.0.dist-info/RECORD
