Metadata-Version: 2.1
Name: odoo12-addon-telecom
Version: 12.0.0.1.0
Summary: Vertical Telecom
Home-page: https://coopdevs.org
Author: Coopdevs Treball SCCL
License: UNKNOWN
Platform: UNKNOWN
Classifier: Programming Language :: Python
Classifier: Framework :: Odoo
Classifier: Framework :: Odoo :: 12.0
Requires-Python: >=3.5
Requires-Dist: odoo12-addon-account-payment-order (==12.0.2.0.0.99.dev3)
Requires-Dist: odoo12-addon-component-event
Requires-Dist: odoo12-addon-crm-lead-product
Requires-Dist: odoo12-addon-product-contract (==12.0.5.2.1)
Requires-Dist: odoo12-addon-sale-substate
Requires-Dist: odoo (<12.1dev,>=12.0a)
Requires-Dist: python-stdnum (==1.14)
